operacionestest/__init__.py
operacionestest/modulo.py
operacionestestsebas-0.1.2.dist-info/METADATA
operacionestestsebas-0.1.2.dist-info/WHEEL
operacionestestsebas-0.1.2.dist-info/top_level.txt
operacionestestsebas-0.1.2.dist-info/RECORD
